{
    "name": "Binary Search",
    "content": "In computer science, binary search, also known as half-interval search, logarithmic search, or binary chop, is a search algorithm that finds the position of a target value within a sorted array. Binary search compares the target value to the middle element of the array. If they are not equal, the half in which the target cannot lie is eliminated and the search continues on the remaining half, again taking the middle element to compare to the target value, and repeating this until the target value is found. If the search ends with the remaining half being empty, the target is not in the array. Even though the idea is simple, implementing binary search correctly requires attention to some subtleties about its exit conditions and midpoint calculation, particularly if the values in the array are not all of the whole numbers in the range.Binary search runs in logarithmic time in the worst case, making O(log n) comparisons, where n is the number of elements in the array, the O is Big O notation, and log is the logarithm. Binary search takes constant (O(1)) space, meaning that the space taken by the algorithm is the same for any number of elements in the array. Binary search is faster than linear search except for small arrays, but the array must be sorted first. Although specialized data structures designed for fast searching, such as hash tables, can be searched more efficiently, binary search applies to a wider range of problems.There are numerous variations of binary search. In particular, fractional cascading speeds up binary searches for the same value in multiple arrays. Fractional cascading efficiently solves a number of search problems in computational geometry and in numerous other fields. Exponential search extends binary search to unbounded lists. The binary search tree and B-tree data structures are based on binary search.\n\t<pre style='background-color: rgb(248, 249, 250); border: 1px solid rgb(234, 236, 240); padding: 1em; line-height: 1.3em; overflow-x: hidden; overflow-wrap: break-word; font-size: 14px;'><b>function</b> binary_search(A, n, T):\n\tL&nbsp;:= 0\n\tR&nbsp;:= n − 1\n\t<b>while</b> L &lt;= R:\n\t\tm&nbsp;:= floor((L + R) / 2)\n\t\t<b>if</b> A[m] &lt; T:\n\t\t\tL&nbsp;:= m + 1\n\t\t<b>else if</b> A[m] &gt; T:\n\t\t\tR&nbsp;:= m - 1\n\t\t<b>else</b>:\n\t\t\t<b>return</b> m\n\t<b>return</b> unsuccessful</pre>",
    "quiz": [
        {
            "question": "What is Binary Search?",
            "answers": [
                "A hologram of the Demon",
                "A hero from BNH Academia",
                "Algorithm based on duality of the truthness and the falseness",
                "No Idea ... I am just a potato around here..."
            ],
            "correct": 2
        }
    ],
    "nextLessonName": "graph"
}